Workbook

Sheet Resumen
B1: Inconsistencia en el Estado de Resultado Integral · julio y agosto 2026
B2: JURIDICA ABOGADOS Y CONSULTORES S.A.S. · NIT 900.944.440-3
B3: Fuente: PDF «EEFF DE JURIDICA AGOSTO», Estado de Resultado Integral acumulado a 31 de agosto de 2026, páginas 3 y 4.
B5: ¿CUÁL ES LA DUDA?
B6: En las columnas de JULIO y AGOSTO, el subtotal «Costo de personal (mano obra indirecta)» aparece en cero, aunque sus partidas (asesoría jurídica, gastos de viaje e intangibles) sí tienen valor. Por eso el «Total costos de operación» de esos meses solo suma la mano de obra directa, y la utilidad bruta, operacional y neta de julio y agosto quedan más altas de lo que deberían. La columna ACUMULADO sí incluye esos valores, así que el acumulado y el balance están bien.
B8: CIFRAS CLAVE
B9: Concepto | C9: Julio | D9: Agosto | E9: Total
B10: Mano de obra indirecta que no se sumó (hoja 1) | C10: ='1. Costos'!H14 -> 5885521 | D10: ='1. Costos'!I14 -> 7087256 | E10: =C10+D10 -> 12972777
B11: Total costos de operación · según PDF | C11: ='3. ER corregido'!B18 -> 15460182 | D11: ='3. ER corregido'!E18 -> 16243670
B12: Total costos de operación · corregido | C12: ='3. ER corregido'!C18 -> 21345703 | D12: ='3. ER corregido'!F18 -> 23330926
B13: Utilidad neta del mes · según PDF | C13: ='3. ER corregido'!B22 -> 33091251 | D13: ='3. ER corregido'!E22 -> 13274089
B14: Utilidad neta del mes · corregida | C14: ='3. ER corregido'!C22 -> 27205731 | D14: ='3. ER corregido'!F22 -> 6186833
B16: COMPROBACIÓN (hoja 2)
B17: Suma de las utilidades mensuales impresas en el PDF | C17: ='2. Cuadre acumulado'!J14 -> 210320201
B18: Utilidad acumulada impresa en el PDF (= balance a 31 de agosto) | C18: ='2. Cuadre acumulado'!K14 -> 197347425
B19: Diferencia | C19: =C17-C18 -> 12972776
B20: Mano de obra indirecta omitida en julio y agosto | C20: =E10 -> 12972777
B21: ¿La omisión explica toda la diferencia? (tolerancia $1) | C21: =IF(ABS(C19-C20)<=1,"SÍ, cuadra","NO") -> SÍ, cuadra
B23: LO QUE NECESITAMOS CONFIRMAR
A24: 1. | B24: ¿Se corrige el subtotal de mano de obra indirecta de julio y agosto en el Estado de Resultado Integral, para que el total de costos y la utilidad de esos meses incluyan estas partidas? (La presentación de agosto ya se armó con las cifras corregidas.)
A25: 2. | B25: Duda menor (hoja 4): el balance de julio muestra $363.104 menos de utilidad que el ER actual acumulado a julio. ¿Hubo un ajuste en el ER después de cerrar el balance de julio? Agosto cuadra exactamente.
A26: 3. | B26: Duda menor: las cifras de junio cambiaron frente al informe anterior (utilidad neta de junio: 28.074.688 antes, 24.484.035 ahora). ¿Corresponde a un ajuste o reclasificación ya aprobado?
B28: CÓMO LEER EL ARCHIVO
B29: Hoja 1 · Costos: vuelve a sumar las partidas de mano de obra indirecta y muestra que en julio y agosto el subtotal impreso es cero.
B30: Hoja 2 · Cuadre acumulado: suma los meses del PDF y los compara con la columna ACUMULADO; solo difieren las filas afectadas.
B31: Hoja 3 · ER corregido: recalcula el estado de resultados con la corrección; ahora cuadra con el acumulado del PDF.
B32: Hoja 4 · Balance: compara la utilidad acumulada con el balance de julio y agosto.
B33: Colores: azul = cifra copiada del PDF · negro = fórmula · fondo rojo = diferencia encontrada · fondo turquesa = cuadra.

Sheet 1. Costos
A1: Paso 1 · El subtotal de mano de obra indirecta de julio y agosto está en cero
A2: Se vuelven a sumar las partidas del PDF y se compara con el subtotal impreso. Fuente: PDF «EEFF DE JURIDICA AGOSTO», Estado de Resultado Integral acumulado a 31 de agosto de 2026, páginas 3 y 4.
A3: Azul = cifra copiada del PDF · Negro = fórmula · Rojo = diferencia encontrada
A4: Concepto | B4: Enero | C4: Febrero | D4: Marzo | E4: Abril | F4: Mayo | G4: Junio | H4: Julio | I4: Agosto | J4: Suma de los meses | K4: Acumulado PDF | L4: Diferencia
A5: COSTO DE PERSONAL (MANO OBRA INDIRECTA) · partidas
A6: Asesoría jurídica | B6: 4400000 | C6: 4400000 | D6: 4400000 | E6: 4400000 | F6: 4400000 | G6: 4400000 | H6: 4834187 | I6: 4838028 | J6: =SUM(B6:I6) -> 36072215 | K6: 36072215 | L6: =ROUND(J6-K6,0) -> 0
A7: Vigilancia judicial | B7: 0 | C7: 230552 | D7: 388095 | E7: 426505 | F7: 422664 | G7: 434187 | H7: 0 | I7: 0 | J7: =SUM(B7:I7) -> 1902003 | K7: 1902003 | L7: =ROUND(J7-K7,0) -> 0
A8: Gastos de viaje | B8: 0 | C8: 242017 | D8: 0 | E8: 0 | F8: 0 | G8: 0 | H8: 0 | I8: 1197894 | J8: =SUM(B8:I8) -> 1439911 | K8: 1439911 | L8: =ROUND(J8-K8,0) -> 0
A9: Intangibles | B9: 500345 | C9: 500345 | D9: 500345 | E9: 500345 | F9: 500345 | G9: 1051334 | H9: 1051334 | I9: 1051334 | J9: =SUM(B9:I9) -> 5655727 | K9: 5655727 | L9: =ROUND(J9-K9,0) -> 0
A10: Diversos | B10: 160000 | C10: 160000 | D10: 160000 | E10: 160000 | F10: 154667 | G10: 0 | H10: 0 | I10: 0 | J10: =SUM(B10:I10) -> 794667 | K10: 794667 | L10: =ROUND(J10-K10,0) -> 0
A12: Subtotal mano de obra indirecta · IMPRESO en el PDF | B12: 5060345 | C12: 5532914 | D12: 5448440 | E12: 5486850 | F12: 5477676 | G12: 5885521 | H12: 0 | I12: 0 | J12: =SUM(B12:I12) -> 32891746 | K12: 45864523 | L12: =ROUND(J12-K12,0) -> -12972777
A13: Subtotal mano de obra indirecta · SUMA de las partidas | B13: =SUM(B6:B10) -> 5060345 | C13: =SUM(C6:C10) -> 5532914 | D13: =SUM(D6:D10) -> 5448440 | E13: =SUM(E6:E10) -> 5486850 | F13: =SUM(F6:F10) -> 5477676 | G13: =SUM(G6:G10) -> 5885521 | H13: =SUM(H6:H10) -> 5885521 | I13: =SUM(I6:I10) -> 7087256 | J13: =SUM(B13:I13) -> 45864523 | K13: 45864523 | L13: =ROUND(J13-K13,0) -> 0
A14: ► Mano de obra indirecta NO sumada en el subtotal | B14: =B13-B12 -> 0 | C14: =C13-C12 -> 0 | D14: =D13-D12 -> 0 | E14: =E13-E12 -> 0 | F14: =F13-F12 -> 0 | G14: =G13-G12 -> 0 | H14: =H13-H12 -> 5885521 | I14: =I13-I12 -> 7087256 | J14: =SUM(B14:I14) -> 12972777
A16: TOTAL COSTOS DE OPERACIÓN
A17: Costo de personal (mano obra directa) · impreso | B17: 14368426 | C17: 13769040 | D17: 14235755 | E17: 14771545 | F17: 16710586 | G17: 12265911 | H17: 15460182 | I17: 16243670 | J17: =SUM(B17:I17) -> 117825115 | K17: 117825115 | L17: =ROUND(J17-K17,0) -> 0
A18: Total costos de operación · IMPRESO en el PDF | B18: 19428771 | C18: 19301954 | D18: 19684195 | E18: 20258395 | F18: 22188262 | G18: 18151432 | H18: 15460182 | I18: 16243670 | J18: =SUM(B18:I18) -> 150716861 | K18: 163689638 | L18: =ROUND(J18-K18,0) -> -12972777
A19: Total costos de operación · CORRECTO (directa + indirecta) | B19: =B17+B13 -> 19428771 | C19: =C17+C13 -> 19301954 | D19: =D17+D13 -> 19684195 | E19: =E17+E13 -> 20258395 | F19: =F17+F13 -> 22188262 | G19: =G17+G13 -> 18151432 | H19: =H17+H13 -> 21345703 | I19: =I17+I13 -> 23330926 | J19: =SUM(B19:I19) -> 163689638 | K19: 163689638 | L19: =ROUND(J19-K19,0) -> 0
A20: ► Costos que faltan en el total del mes | B20: =B19-B18 -> 0 | C20: =C19-C18 -> 0 | D20: =D19-D18 -> 0 | E20: =E19-E18 -> 0 | F20: =F19-F18 -> 0 | G20: =G19-G18 -> 0 | H20: =H19-H18 -> 5885521 | I20: =I19-I18 -> 7087256 | J20: =SUM(B20:I20) -> 12972777
A22: Cómo leer esta hoja:
A23: • De enero a junio, el subtotal impreso coincide con la suma de las partidas (diferencia cero).
A24: • En julio y agosto el subtotal impreso es cero, pero las partidas suman 5.885.521 y 7.087.256.
A25: • La columna «Acumulado PDF» sí incluye esos valores: por eso la fila corregida cuadra con el acumulado y la impresa no.

Sheet 2. Cuadre acumulado
A1: Paso 2 · ¿La suma de los meses da el acumulado del PDF?
A2: Cada fila suma enero–agosto tal como están impresos y lo compara con la columna ACUMULADO del PDF. Fuente: PDF «EEFF DE JURIDICA AGOSTO», Estado de Resultado Integral acumulado a 31 de agosto de 2026, páginas 3 y 4.
A3: Las filas en rojo no cuadran: todas difieren exactamente en la mano de obra indirecta omitida (5.885.521 + 7.087.256 = 12.972.777).
A4: Concepto | B4: Enero | C4: Febrero | D4: Marzo | E4: Abril | F4: Mayo | G4: Junio | H4: Julio | I4: Agosto | J4: Suma de los meses | K4: Acumulado PDF | L4: Diferencia
A5: Total ingresos netos | B5: 63161460 | C5: 70894572 | D5: 74422717 | E5: 73518795 | F5: 91144572 | G5: 102167217 | H5: 75012054 | I5: 68648289 | J5: =SUM(B5:I5) -> 618969676 | K5: 618969676 | L5: =ROUND(J5-K5,0) -> 0
A6: Total costos de operación | B6: 19428771 | C6: 19301954 | D6: 19684195 | E6: 20258395 | F6: 22188262 | G6: 18151432 | H6: 15460182 | I6: 16243670 | J6: =SUM(B6:I6) -> 150716861 | K6: 163689638 | L6: =ROUND(J6-K6,0) -> -12972777
A7: Utilidad bruta operacional | B7: 43732689 | C7: 51592618 | D7: 54738522 | E7: 53260400 | F7: 68956310 | G7: 84015785 | H7: 59551872 | I7: 52404619 | J7: =SUM(B7:I7) -> 468252815 | K7: 455280038 | L7: =ROUND(J7-K7,0) -> 12972777
A8: Total gastos de administración y ventas | B8: 28644316 | C8: 36206194 | D8: 19657780 | E8: 53519267 | F8: 23905588 | G8: 98058387 | H8: 37671013 | I8: 40769091 | J8: =SUM(B8:I8) -> 338431636 | K8: 338431636 | L8: =ROUND(J8-K8,0) -> 0
A9: Resultado operacional | B9: 15088373 | C9: 15386424 | D9: 35080742 | E9: -258867 | F9: 45050722 | G9: -14042602 | H9: 21880859 | I9: 11635528 | J9: =SUM(B9:I9) -> 129821179 | K9: 116848402 | L9: =ROUND(J9-K9,0) -> 12972777
A10: (+) Ingresos no operacionales | B10: 14479.12 | C10: 28512.09 | D10: 19642.15 | E10: 63242453 | F10: 26514220 | G10: 1.0263382e+08 | H10: 32436522 | I10: 35543022 | J10: =SUM(B10:I10) -> 2.6043267e+08 | K10: 2.6043267e+08 | L10: =ROUND(J10-K10,0) -> 0
A11: (−) Gastos no operacionales | B11: 735455 | C11: 603190 | D11: 726548 | E11: 16545842 | F11: 940840 | G11: 35490180 | H11: 21226129 | I11: 11035461 | J11: =SUM(B11:I11) -> 87303645 | K11: 87303644 | L11: =ROUND(J11-K11,0) -> 1
A12: Resultado antes de impuesto | B12: 14367398 | C12: 14811746 | D12: 34373836 | E12: 46437744 | F12: 70624102 | G12: 53101035 | H12: 33091251 | I12: 36143089 | J12: =SUM(B12:I12) -> 302950201 | K12: 289977425 | L12: =ROUND(J12-K12,0) -> 12972776
A13: Impuesto SIMPLE | B13: 0 | C13: 13151000 | D13: 0 | E13: 27993000 | F13: 0 | G13: 28617000 | H13: 0 | I13: 22869000 | J13: =SUM(B13:I13) -> 92630000 | K13: 92630000 | L13: =ROUND(J13-K13,0) -> 0
A14: Resultado del ejercicio | B14: 14367398 | C14: 1660746 | D14: 34373836 | E14: 18444744 | F14: 70624102 | G14: 24484035 | H14: 33091251 | I14: 13274089 | J14: =SUM(B14:I14) -> 210320201 | K14: 197347425 | L14: =ROUND(J14-K14,0) -> 12972776
A16: Diferencia en «Resultado del ejercicio» | L16: =L14 -> 12972776
A17: Mano de obra indirecta omitida (julio + agosto, hoja 1) | L17: ='1. Costos'!H14+'1. Costos'!I14 -> 12972777
A18: ¿Explica toda la diferencia? (tolerancia $1 por decimales del PDF) | L18: =IF(ABS(L16-L17)<=1,"SÍ, cuadra","NO") -> SÍ, cuadra
A20: Cómo leer esta hoja:
A21: • Ingresos, gastos de administración, partidas no operacionales e impuesto cuadran (diferencia cero, o $1 por los decimales del PDF).
A22: • Desde «Total costos de operación» hacia abajo, todas las filas difieren en 12.972.777 (los costos por debajo; las utilidades por encima).
A23: • Esa cifra es exactamente la mano de obra indirecta de julio y agosto que no se sumó (hoja 1). El error está solo en esas dos columnas.

Sheet 3. ER corregido
A1: Paso 3 · Estado de resultados recalculado con la mano de obra indirecta incluida
A2: Todas las filas son fórmulas sobre las hojas 1 y 2. La última columna compara con el ACUMULADO del PDF.
A4: Concepto | B4: Enero | C4: Febrero | D4: Marzo | E4: Abril | F4: Mayo | G4: Junio | H4: Julio | I4: Agosto | J4: Suma de los meses | K4: Acumulado PDF | L4: Diferencia
A5: Total ingresos netos | B5: ='2. Cuadre acumulado'!B5 -> 63161460 | C5: ='2. Cuadre acumulado'!C5 -> 70894572 | D5: ='2. Cuadre acumulado'!D5 -> 74422717 | E5: ='2. Cuadre acumulado'!E5 -> 73518795 | F5: ='2. Cuadre acumulado'!F5 -> 91144572 | G5: ='2. Cuadre acumulado'!G5 -> 102167217 | H5: ='2. Cuadre acumulado'!H5 -> 75012054 | I5: ='2. Cuadre acumulado'!I5 -> 68648289 | J5: =SUM(B5:I5) -> 618969676 | K5: ='2. Cuadre acumulado'!K5 -> 618969676 | L5: =ROUND(J5-K5,0) -> 0
A6: Total costos de operación (corregido) | B6: ='1. Costos'!B19 -> 19428771 | C6: ='1. Costos'!C19 -> 19301954 | D6: ='1. Costos'!D19 -> 19684195 | E6: ='1. Costos'!E19 -> 20258395 | F6: ='1. Costos'!F19 -> 22188262 | G6: ='1. Costos'!G19 -> 18151432 | H6: ='1. Costos'!H19 -> 21345703 | I6: ='1. Costos'!I19 -> 23330926 | J6: =SUM(B6:I6) -> 163689638 | K6: ='2. Cuadre acumulado'!K6 -> 163689638 | L6: =ROUND(J6-K6,0) -> 0
A7: Utilidad bruta operacional | B7: =B5-B6 -> 43732689 | C7: =C5-C6 -> 51592618 | D7: =D5-D6 -> 54738522 | E7: =E5-E6 -> 53260400 | F7: =F5-F6 -> 68956310 | G7: =G5-G6 -> 84015785 | H7: =H5-H6 -> 53666351 | I7: =I5-I6 -> 45317363 | J7: =SUM(B7:I7) -> 455280038 | K7: ='2. Cuadre acumulado'!K7 -> 455280038 | L7: =ROUND(J7-K7,0) -> 0
A8: Total gastos de administración y ventas | B8: ='2. Cuadre acumulado'!B8 -> 28644316 | C8: ='2. Cuadre acumulado'!C8 -> 36206194 | D8: ='2. Cuadre acumulado'!D8 -> 19657780 | E8: ='2. Cuadre acumulado'!E8 -> 53519267 | F8: ='2. Cuadre acumulado'!F8 -> 23905588 | G8: ='2. Cuadre acumulado'!G8 -> 98058387 | H8: ='2. Cuadre acumulado'!H8 -> 37671013 | I8: ='2. Cuadre acumulado'!I8 -> 40769091 | J8: =SUM(B8:I8) -> 338431636 | K8: ='2. Cuadre acumulado'!K8 -> 338431636 | L8: =ROUND(J8-K8,0) -> 0
A9: Resultado operacional | B9: =B7-B8 -> 15088373 | C9: =C7-C8 -> 15386424 | D9: =D7-D8 -> 35080742 | E9: =E7-E8 -> -258867 | F9: =F7-F8 -> 45050722 | G9: =G7-G8 -> -14042602 | H9: =H7-H8 -> 15995338 | I9: =I7-I8 -> 4548272 | J9: =SUM(B9:I9) -> 116848402 | K9: ='2. Cuadre acumulado'!K9 -> 116848402 | L9: =ROUND(J9-K9,0) -> 0
A10: (+) Ingresos no operacionales | B10: ='2. Cuadre acumulado'!B10 -> 14479.12 | C10: ='2. Cuadre acumulado'!C10 -> 28512.09 | D10: ='2. Cuadre acumulado'!D10 -> 19642.15 | E10: ='2. Cuadre acumulado'!E10 -> 63242453 | F10: ='2. Cuadre acumulado'!F10 -> 26514220 | G10: ='2. Cuadre acumulado'!G10 -> 1.0263382e+08 | H10: ='2. Cuadre acumulado'!H10 -> 32436522 | I10: ='2. Cuadre acumulado'!I10 -> 35543022 | J10: =SUM(B10:I10) -> 2.6043267e+08 | K10: ='2. Cuadre acumulado'!K10 -> 2.6043267e+08 | L10: =ROUND(J10-K10,0) -> 0
A11: (−) Gastos no operacionales | B11: ='2. Cuadre acumulado'!B11 -> 735455 | C11: ='2. Cuadre acumulado'!C11 -> 603190 | D11: ='2. Cuadre acumulado'!D11 -> 726548 | E11: ='2. Cuadre acumulado'!E11 -> 16545842 | F11: ='2. Cuadre acumulado'!F11 -> 940840 | G11: ='2. Cuadre acumulado'!G11 -> 35490180 | H11: ='2. Cuadre acumulado'!H11 -> 21226129 | I11: ='2. Cuadre acumulado'!I11 -> 11035461 | J11: =SUM(B11:I11) -> 87303645 | K11: ='2. Cuadre acumulado'!K11 -> 87303644 | L11: =ROUND(J11-K11,0) -> 1
A12: Resultado antes de impuesto | B12: =B9+B10-B11 -> 14367397 | C12: =C9+C10-C11 -> 14811746 | D12: =D9+D10-D11 -> 34373836 | E12: =E9+E10-E11 -> 46437744 | F12: =F9+F10-F11 -> 70624102 | G12: =G9+G10-G11 -> 53101035 | H12: =H9+H10-H11 -> 27205731 | I12: =I9+I10-I11 -> 29055833 | J12: =SUM(B12:I12) -> 2.8997742e+08 | K12: ='2. Cuadre acumulado'!K12 -> 289977425 | L12: =ROUND(J12-K12,0) -> -1
A13: Impuesto SIMPLE | B13: ='2. Cuadre acumulado'!B13 -> 0 | C13: ='2. Cuadre acumulado'!C13 -> 13151000 | D13: ='2. Cuadre acumulado'!D13 -> 0 | E13: ='2. Cuadre acumulado'!E13 -> 27993000 | F13: ='2. Cuadre acumulado'!F13 -> 0 | G13: ='2. Cuadre acumulado'!G13 -> 28617000 | H13: ='2. Cuadre acumulado'!H13 -> 0 | I13: ='2. Cuadre acumulado'!I13 -> 22869000 | J13: =SUM(B13:I13) -> 92630000 | K13: ='2. Cuadre acumulado'!K13 -> 92630000 | L13: =ROUND(J13-K13,0) -> 0
A14: Resultado del ejercicio (corregido) | B14: =B12-B13 -> 14367397 | C14: =C12-C13 -> 1660746.1 | D14: =D12-D13 -> 34373836 | E14: =E12-E13 -> 18444744 | F14: =F12-F13 -> 70624102 | G14: =G12-G13 -> 24484035 | H14: =H12-H13 -> 27205731 | I14: =I12-I13 -> 6186833 | J14: =SUM(B14:I14) -> 1.9734742e+08 | K14: ='2. Cuadre acumulado'!K14 -> 197347425 | L14: =ROUND(J14-K14,0) -> -1
A16: IMPRESO vs CORREGIDO · julio y agosto
A17: Concepto | B17: Julio · PDF | C17: Julio · corregido | D17: Diferencia | E17: Agosto · PDF | F17: Agosto · corregido | G17: Diferencia
A18: Total costos de operación | B18: ='2. Cuadre acumulado'!H6 -> 15460182 | C18: =H6 -> 21345703 | D18: =C18-B18 -> 5885521 | E18: ='2. Cuadre acumulado'!I6 -> 16243670 | F18: =I6 -> 23330926 | G18: =F18-E18 -> 7087256
A19: Utilidad bruta operacional | B19: ='2. Cuadre acumulado'!H7 -> 59551872 | C19: =H7 -> 53666351 | D19: =C19-B19 -> -5885521 | E19: ='2. Cuadre acumulado'!I7 -> 52404619 | F19: =I7 -> 45317363 | G19: =F19-E19 -> -7087256
A20: Resultado operacional | B20: ='2. Cuadre acumulado'!H9 -> 21880859 | C20: =H9 -> 15995338 | D20: =C20-B20 -> -5885521 | E20: ='2. Cuadre acumulado'!I9 -> 11635528 | F20: =I9 -> 4548272 | G20: =F20-E20 -> -7087256
A21: Resultado antes de impuesto | B21: ='2. Cuadre acumulado'!H12 -> 33091251 | C21: =H12 -> 27205731 | D21: =C21-B21 -> -5885520.1 | E21: ='2. Cuadre acumulado'!I12 -> 36143089 | F21: =I12 -> 29055833 | G21: =F21-E21 -> -7087256
A22: Resultado del ejercicio | B22: ='2. Cuadre acumulado'!H14 -> 33091251 | C22: =H14 -> 27205731 | D22: =C22-B22 -> -5885520.1 | E22: ='2. Cuadre acumulado'!I14 -> 13274089 | F22: =I14 -> 6186833 | G22: =F22-E22 -> -7087256

Sheet 4. Balance
A1: Paso 4 · Cuadre con el balance (resultado del ejercicio)
A2: Compara la utilidad acumulada del ER corregido con la cuenta «Resultado del ejercicio» del Estado de Situación Financiera (página 2 del PDF).
A4: Concepto | B4: A 31 de julio | C4: A 31 de agosto | D4: Movimiento de agosto
A5: Resultado del ejercicio · balance (PDF) | B5: 190797487 | C5: 197347425 | D5: =C5-B5 -> 6549938
A6: Utilidad acumulada · ER corregido (hoja 3) | B6: =SUM('3. ER corregido'!B14:H14) -> 1.9116059e+08 | C6: =SUM('3. ER corregido'!B14:I14) -> 1.9734742e+08 | D6: =C6-B6 -> 6186833
A7: Diferencia (balance − ER) | B7: =ROUND(B5-B6,0) -> -363104 | C7: =ROUND(C5-C6,0) -> 1 | D7: =ROUND(D5-D6,0) -> 363105
A9: Cómo leer esta hoja:
A10: • A 31 de agosto, el balance cuadra exactamente con el ER corregido: confirma que el acumulado del PDF es el correcto.
A11: • A 31 de julio hay una diferencia menor: el balance de julio muestra menos utilidad que el ER actual hasta julio.
A12: Posible ajuste registrado en el ER después de cerrar el balance de julio. Es una duda aparte y de bajo monto.
